run_one/__init__.py
run_one/action_handlers/SleepHandler.py
run_one/action_handlers/TH2ActHandler.py
run_one/action_handlers/TH2ActSSHHandler.py
run_one/action_handlers/TH2Check1Handler.py
run_one/action_handlers/TH2EstoreHandler.py
run_one/action_handlers/__init__.py
run_one/action_handlers/abstract_action_handler.py
run_one/action_handlers/context.py
run_one/processors/__init__.py
run_one/processors/abstract_processor.py
run_one/processors/th2_processor.py
run_one/util/__init__.py
run_one/util/config.py
run_one/util/util.py
run_one-1.2.9.dist-info/LICENSE
run_one-1.2.9.dist-info/METADATA
run_one-1.2.9.dist-info/WHEEL
run_one-1.2.9.dist-info/RECORD
