Metadata-Version: 2.1
Name: run-one
Version: 1.2.9
Summary: Tool for parsing matrix files, extracting actions and processing them according to user defined logic
Home-page: https://github.com/th2-net/run-one
License: Apache-2.0
Author: TH2-devs
Author-email: th2-devs@exactprosystems.com
Requires-Python: >=3.9,<4.0
Classifier: License :: OSI Approved :: Apache Software License
Classifier: Programming Language :: Python :: 3
Classifier: Programming Language :: Python :: 3.9
Classifier: Programming Language :: Python :: 3.10
Classifier: Programming Language :: Python :: 3.11
Classifier: Programming Language :: Python :: 3.12
Provides-Extra: th2
Requires-Dist: pyyaml (>=6.0,<7.0)
Requires-Dist: th2-common (>=4,<5) ; extra == "th2"
Requires-Dist: th2-grpc-act-ssh (>=2,<3) ; extra == "th2"
Requires-Dist: th2-grpc-act-template (>=4.0.1,<5.0.0) ; extra == "th2"
Requires-Dist: th2-grpc-check1 (>=4.1.1,<5.0.0) ; extra == "th2"
Project-URL: Repository, https://github.com/th2-net/run-one
